git_release_tagger/__init__.py
git_release_tagger/git_tagger.py
git_release_tagger-0.0.2.data/scripts/tag-release
git_release_tagger-0.0.2.dist-info/DESCRIPTION.rst
git_release_tagger-0.0.2.dist-info/METADATA
git_release_tagger-0.0.2.dist-info/RECORD
git_release_tagger-0.0.2.dist-info/WHEEL
git_release_tagger-0.0.2.dist-info/metadata.json
git_release_tagger-0.0.2.dist-info/top_level.txt
