Metadata-Version: 2.0
Name: git-release-tagger
Version: 0.0.2
Summary: Small CLI utility to enable the CI environment to communicate the deployment progress through the use of git tags.
Home-page: https://github.com/SwingDev/git-release-tagger
Author: Tomek Kopczuk
Author-email: tkopczuk@gmail.com
License: LICENSE
Platform: UNKNOWN
Classifier: Development Status :: 3 - Alpha
Classifier: Intended Audience :: Developers
Classifier: Natural Language :: English
Classifier: License :: OSI Approved :: MIT License
Classifier: Programming Language :: Python
Classifier: Programming Language :: Python :: 2.7
Requires-Dist: argparse (>=1.4.0)
Requires-Dist: envoy (>=0.0.3)
